Workbook

Sheet Dashboard
A1: Sales Performance Dashboard - 2026
A2: Select a branch in B4. All figures and charts update automatically. (Sample data - fictional)
A4: Branch filter: | B4: All | C4: =IF($B$4="All","*",$B$4) -> * | D4: <- helper cell (do not edit)
A6: Total Revenue | B6: Total Profit | C6: Profit Margin | D6: Units Sold | E6: Transactions
A7: =SUMIFS(Data!$I$2:$I$601,Data!$C$2:$C$601,$C$4) -> 13337500 | B7: =SUMIFS(Data!$J$2:$J$601,Data!$C$2:$C$601,$C$4) -> 2799440 | C7: =IF(A7=0,0,B7/A7) -> 0.20989241 | D7: =SUMIFS(Data!$F$2:$F$601,Data!$C$2:$C$601,$C$4) -> 3711 | E7: =COUNTIFS(Data!$C$2:$C$601,$C$4) -> 600
A9: Monthly Trend
A10: Month | B10: Revenue | C10: Profit
A11: Jan | B11: =SUMIFS(Data!$I$2:$I$601,Data!$B$2:$B$601,ROW()-10,Data!$C$2:$C$601,$C$4) -> 877300 | C11: =SUMIFS(Data!$J$2:$J$601,Data!$B$2:$B$601,ROW()-10,Data!$C$2:$C$601,$C$4) -> 188520
A12: Feb | B12: =SUMIFS(Data!$I$2:$I$601,Data!$B$2:$B$601,ROW()-10,Data!$C$2:$C$601,$C$4) -> 619400 | C12: =SUMIFS(Data!$J$2:$J$601,Data!$B$2:$B$601,ROW()-10,Data!$C$2:$C$601,$C$4) -> 135030
A13: Mar | B13: =SUMIFS(Data!$I$2:$I$601,Data!$B$2:$B$601,ROW()-10,Data!$C$2:$C$601,$C$4) -> 1078500 | C13: =SUMIFS(Data!$J$2:$J$601,Data!$B$2:$B$601,ROW()-10,Data!$C$2:$C$601,$C$4) -> 225690
A14: Apr | B14: =SUMIFS(Data!$I$2:$I$601,Data!$B$2:$B$601,ROW()-10,Data!$C$2:$C$601,$C$4) -> 1019250 | C14: =SUMIFS(Data!$J$2:$J$601,Data!$B$2:$B$601,ROW()-10,Data!$C$2:$C$601,$C$4) -> 223360
A15: May | B15: =SUMIFS(Data!$I$2:$I$601,Data!$B$2:$B$601,ROW()-10,Data!$C$2:$C$601,$C$4) -> 1435100 | C15: =SUMIFS(Data!$J$2:$J$601,Data!$B$2:$B$601,ROW()-10,Data!$C$2:$C$601,$C$4) -> 289670
A16: Jun | B16: =SUMIFS(Data!$I$2:$I$601,Data!$B$2:$B$601,ROW()-10,Data!$C$2:$C$601,$C$4) -> 700200 | C16: =SUMIFS(Data!$J$2:$J$601,Data!$B$2:$B$601,ROW()-10,Data!$C$2:$C$601,$C$4) -> 155630
A17: Jul | B17: =SUMIFS(Data!$I$2:$I$601,Data!$B$2:$B$601,ROW()-10,Data!$C$2:$C$601,$C$4) -> 1268400 | C17: =SUMIFS(Data!$J$2:$J$601,Data!$B$2:$B$601,ROW()-10,Data!$C$2:$C$601,$C$4) -> 259910
A18: Aug | B18: =SUMIFS(Data!$I$2:$I$601,Data!$B$2:$B$601,ROW()-10,Data!$C$2:$C$601,$C$4) -> 1427550 | C18: =SUMIFS(Data!$J$2:$J$601,Data!$B$2:$B$601,ROW()-10,Data!$C$2:$C$601,$C$4) -> 297780
A19: Sep | B19: =SUMIFS(Data!$I$2:$I$601,Data!$B$2:$B$601,ROW()-10,Data!$C$2:$C$601,$C$4) -> 1336200 | C19: =SUMIFS(Data!$J$2:$J$601,Data!$B$2:$B$601,ROW()-10,Data!$C$2:$C$601,$C$4) -> 275280
A20: Oct | B20: =SUMIFS(Data!$I$2:$I$601,Data!$B$2:$B$601,ROW()-10,Data!$C$2:$C$601,$C$4) -> 1169650 | C20: =SUMIFS(Data!$J$2:$J$601,Data!$B$2:$B$601,ROW()-10,Data!$C$2:$C$601,$C$4) -> 245060
A21: Nov | B21: =SUMIFS(Data!$I$2:$I$601,Data!$B$2:$B$601,ROW()-10,Data!$C$2:$C$601,$C$4) -> 1201900 | C21: =SUMIFS(Data!$J$2:$J$601,Data!$B$2:$B$601,ROW()-10,Data!$C$2:$C$601,$C$4) -> 253790
A22: Dec | B22: =SUMIFS(Data!$I$2:$I$601,Data!$B$2:$B$601,ROW()-10,Data!$C$2:$C$601,$C$4) -> 1204050 | C22: =SUMIFS(Data!$J$2:$J$601,Data!$B$2:$B$601,ROW()-10,Data!$C$2:$C$601,$C$4) -> 249720
A24: Sales by Product
A25: Product | B25: Revenue | C25: Profit | D25: Units | E25: Share of Revenue
A26: Laptop | B26: =SUMIFS(Data!$I$2:$I$601,Data!$D$2:$D$601,$A26,Data!$C$2:$C$601,$C$4) -> 7899500 | C26: =SUMIFS(Data!$J$2:$J$601,Data!$D$2:$D$601,$A26,Data!$C$2:$C$601,$C$4) -> 1494500 | D26: =SUMIFS(Data!$F$2:$F$601,Data!$D$2:$D$601,$A26,Data!$C$2:$C$601,$C$4) -> 427 | E26: =IF($A$7=0,0,B26/$A$7) -> 0.59227741
A27: Monitor | B27: =SUMIFS(Data!$I$2:$I$601,Data!$D$2:$D$601,$A27,Data!$C$2:$C$601,$C$4) -> 2129400 | C27: =SUMIFS(Data!$J$2:$J$601,Data!$D$2:$D$601,$A27,Data!$C$2:$C$601,$C$4) -> 456300 | D27: =SUMIFS(Data!$F$2:$F$601,Data!$D$2:$D$601,$A27,Data!$C$2:$C$601,$C$4) -> 507 | E27: =IF($A$7=0,0,B27/$A$7) -> 0.15965511
A28: Printer | B28: =SUMIFS(Data!$I$2:$I$601,Data!$D$2:$D$601,$A28,Data!$C$2:$C$601,$C$4) -> 1941800 | C28: =SUMIFS(Data!$J$2:$J$601,Data!$D$2:$D$601,$A28,Data!$C$2:$C$601,$C$4) -> 408800 | D28: =SUMIFS(Data!$F$2:$F$601,Data!$D$2:$D$601,$A28,Data!$C$2:$C$601,$C$4) -> 511 | E28: =IF($A$7=0,0,B28/$A$7) -> 0.1455895
A29: Keyboard | B29: =SUMIFS(Data!$I$2:$I$601,Data!$D$2:$D$601,$A29,Data!$C$2:$C$601,$C$4) -> 256050 | C29: =SUMIFS(Data!$J$2:$J$601,Data!$D$2:$D$601,$A29,Data!$C$2:$C$601,$C$4) -> 96730 | D29: =SUMIFS(Data!$F$2:$F$601,Data!$D$2:$D$601,$A29,Data!$C$2:$C$601,$C$4) -> 569 | E29: =IF($A$7=0,0,B29/$A$7) -> 0.019197751
A30: Mouse | B30: =SUMIFS(Data!$I$2:$I$601,Data!$D$2:$D$601,$A30,Data!$C$2:$C$601,$C$4) -> 109750 | C30: =SUMIFS(Data!$J$2:$J$601,Data!$D$2:$D$601,$A30,Data!$C$2:$C$601,$C$4) -> 48290 | D30: =SUMIFS(Data!$F$2:$F$601,Data!$D$2:$D$601,$A30,Data!$C$2:$C$601,$C$4) -> 439 | E30: =IF($A$7=0,0,B30/$A$7) -> 0.0082286785
A31: Router | B31: =SUMIFS(Data!$I$2:$I$601,Data!$D$2:$D$601,$A31,Data!$C$2:$C$601,$C$4) -> 541800 | C31: =SUMIFS(Data!$J$2:$J$601,Data!$D$2:$D$601,$A31,Data!$C$2:$C$601,$C$4) -> 150500 | D31: =SUMIFS(Data!$F$2:$F$601,Data!$D$2:$D$601,$A31,Data!$C$2:$C$601,$C$4) -> 602 | E31: =IF($A$7=0,0,B31/$A$7) -> 0.040622306
A32: Webcam | B32: =SUMIFS(Data!$I$2:$I$601,Data!$D$2:$D$601,$A32,Data!$C$2:$C$601,$C$4) -> 459200 | C32: =SUMIFS(Data!$J$2:$J$601,Data!$D$2:$D$601,$A32,Data!$C$2:$C$601,$C$4) -> 144320 | D32: =SUMIFS(Data!$F$2:$F$601,Data!$D$2:$D$601,$A32,Data!$C$2:$C$601,$C$4) -> 656 | E32: =IF($A$7=0,0,B32/$A$7) -> 0.034429241
A34: Branch Comparison (not affected by filter)
A35: Branch | B35: Revenue | C35: Profit | D35: Margin
A36: Cairo | B36: =SUMIFS(Data!$I$2:$I$601,Data!$C$2:$C$601,$A36) -> 3448900 | C36: =SUMIFS(Data!$J$2:$J$601,Data!$C$2:$C$601,$A36) -> 721360 | D36: =IF(B36=0,0,C36/B36) -> 0.20915654
A37: Alexandria | B37: =SUMIFS(Data!$I$2:$I$601,Data!$C$2:$C$601,$A37) -> 3394950 | C37: =SUMIFS(Data!$J$2:$J$601,Data!$C$2:$C$601,$A37) -> 716980 | D37: =IF(B37=0,0,C37/B37) -> 0.21119015
A38: Giza | B38: =SUMIFS(Data!$I$2:$I$601,Data!$C$2:$C$601,$A38) -> 2829200 | C38: =SUMIFS(Data!$J$2:$J$601,Data!$C$2:$C$601,$A38) -> 594640 | D38: =IF(B38=0,0,C38/B38) -> 0.21017956
A39: Mansoura | B39: =SUMIFS(Data!$I$2:$I$601,Data!$C$2:$C$601,$A39) -> 3664450 | C39: =SUMIFS(Data!$J$2:$J$601,Data!$C$2:$C$601,$A39) -> 766460 | D39: =IF(B39=0,0,C39/B39) -> 0.20916099
A40: Best branch: | B40: =INDEX(A36:A39,MATCH(MAX(B36:B39),B36:B39,0)) -> Mansoura

Sheet Data
A1: Date | B1: Month | C1: Branch | D1: Product | E1: Category | F1: Qty | G1: Unit Price | H1: Unit Cost | I1: Revenue | J1: Profit
A2: 46237 | B2: =MONTH(A2) -> 8 | C2: Mansoura | D2: Monitor | E2: Electronics | F2: 11 | G2: 4200 | H2: 3300 | I2: =F2*G2 -> 46200 | J2: =F2*(G2-H2) -> 9900
A3: 46268 | B3: =MONTH(A3) -> 9 | C3: Alexandria | D3: Printer | E3: Electronics | F3: 8 | G3: 3800 | H3: 3000 | I3: =F3*G3 -> 30400 | J3: =F3*(G3-H3) -> 6400
A4: 46285 | B4: =MONTH(A4) -> 9 | C4: Alexandria | D4: Webcam | E4: Accessories | F4: 9 | G4: 700 | H4: 480 | I4: =F4*G4 -> 6300 | J4: =F4*(G4-H4) -> 1980
A5: 46143 | B5: =MONTH(A5) -> 5 | C5: Cairo | D5: Mouse | E5: Accessories | F5: 1 | G5: 250 | H5: 140 | I5: =F5*G5 -> 250 | J5: =F5*(G5-H5) -> 110
A6: 46322 | B6: =MONTH(A6) -> 10 | C6: Mansoura | D6: Printer | E6: Electronics | F6: 2 | G6: 3800 | H6: 3000 | I6: =F6*G6 -> 7600 | J6: =F6*(G6-H6) -> 1600
A7: 46141 | B7: =MONTH(A7) -> 4 | C7: Alexandria | D7: Monitor | E7: Electronics | F7: 12 | G7: 4200 | H7: 3300 | I7: =F7*G7 -> 50400 | J7: =F7*(G7-H7) -> 10800
A8: 46246 | B8: =MONTH(A8) -> 8 | C8: Mansoura | D8: Laptop | E8: Electronics | F8: 10 | G8: 18500 | H8: 15000 | I8: =F8*G8 -> 185000 | J8: =F8*(G8-H8) -> 35000
A9: 46040 | B9: =MONTH(A9) -> 1 | C9: Giza | D9: Keyboard | E9: Accessories | F9: 9 | G9: 450 | H9: 280 | I9: =F9*G9 -> 4050 | J9: =F9*(G9-H9) -> 1530
A10: 46378 | B10: =MONTH(A10) -> 12 | C10: Cairo | D10: Keyboard | E10: Accessories | F10: 11 | G10: 450 | H10: 280 | I10: =F10*G10 -> 4950 | J10: =F10*(G10-H10) -> 1870
A11: 46034 | B11: =MONTH(A11) -> 1 | C11: Alexandria | D11: Printer | E11: Electronics | F11: 12 | G11: 3800 | H11: 3000 | I11: =F11*G11 -> 45600 | J11: =F11*(G11-H11) -> 9600
A12: 46068 | B12: =MONTH(A12) -> 2 | C12: Cairo | D12: Webcam | E12: Accessories | F12: 1 | G12: 700 | H12: 480 | I12: =F12*G12 -> 700 | J12: =F12*(G12-H12) -> 220
A13: 46105 | B13: =MONTH(A13) -> 3 | C13: Giza | D13: Keyboard | E13: Accessories | F13: 7 | G13: 450 | H13: 280 | I13: =F13*G13 -> 3150 | J13: =F13*(G13-H13) -> 1190
... A601: 46141 | B601: =MONTH(A601) -> 4 | C601: Giza | D601: Printer | E601: Electronics | F601: 6 | G601: 3800 | H601: 3000 | I601: =F601*G601 -> 22800 | J601: =F601*(G601-H601) -> 4800
